[
  { "name": "client_id",                  "type": "STRING",    "mode": "REQUIRED", "description": "Tenant identifier" },
  { "name": "source_system",              "type": "STRING",    "mode": "REQUIRED", "description": "Originating data system" },
  { "name": "employee_id",                "type": "STRING",    "mode": "REQUIRED", "description": "Contact PK — joins to dim_contact and lead_scores" },
  { "name": "name",                       "type": "STRING",    "mode": "NULLABLE", "description": "Full name — PII: pii-contact policy tag" },
  { "name": "job_title",                  "type": "STRING",    "mode": "NULLABLE", "description": "Job title" },
  { "name": "seniority_level",            "type": "STRING",    "mode": "NULLABLE", "description": "Seniority band" },
  { "name": "decision_maker_flag",        "type": "STRING",    "mode": "NULLABLE", "description": "'Yes' if purchasing authority" },
  { "name": "influence_score",            "type": "INT64",     "mode": "NULLABLE", "description": "0–100 influence score" },
  { "name": "preferred_contact_method",   "type": "STRING",    "mode": "NULLABLE", "description": "Email | Phone | SMS" },
  { "name": "language",                   "type": "STRING",    "mode": "NULLABLE", "description": "Preferred language" },
  { "name": "email",                      "type": "STRING",    "mode": "NULLABLE", "description": "Email address — PII: pii-contact policy tag" },
  { "name": "phone",                      "type": "STRING",    "mode": "NULLABLE", "description": "Phone number — PII: pii-contact policy tag" },
  { "name": "email_domain",               "type": "STRING",    "mode": "NULLABLE", "description": "Safe surrogate: domain portion of email" },
  { "name": "contact_hash",               "type": "STRING",    "mode": "NULLABLE", "description": "Safe surrogate: SHA-256 hex of email" },
  { "name": "company_id",                 "type": "STRING",    "mode": "REQUIRED", "description": "Account PK — joins to dim_company" },
  { "name": "industry",                   "type": "STRING",    "mode": "NULLABLE", "description": "Industry vertical" },
  { "name": "company_size",               "type": "STRING",    "mode": "NULLABLE", "description": "Headcount band" },
  { "name": "region",                     "type": "STRING",    "mode": "NULLABLE", "description": "Geographic region" },
  { "name": "contract_status",            "type": "STRING",    "mode": "NULLABLE", "description": "Active | Pending | Churned" },
  { "name": "conversion_rate_pct",        "type": "FLOAT64",   "mode": "NULLABLE", "description": "Historical conversion rate %" },
  { "name": "total_purchases_last_year",  "type": "INT64",     "mode": "NULLABLE", "description": "Purchases in trailing 12 months" },
  { "name": "days_since_last_purchase",   "type": "INT64",     "mode": "NULLABLE", "description": "Recency signal for scoring" },
  { "name": "payment_behavior",           "type": "STRING",    "mode": "NULLABLE", "description": "Payment reliability label" },
  { "name": "last_product_1",             "type": "STRING",    "mode": "NULLABLE", "description": "Most recently purchased product" },
  { "name": "loaded_at",                  "type": "TIMESTAMP", "mode": "REQUIRED", "description": "Timestamp when this row was last materialised" }
]
